{"cameraMode":{"drawMode":0,"name":"Shaded","section":"Shading Mode"},"sceneLighting":false,"audioPlay":false,"sceneViewState":{"showFog":true,"showMaterialUpdate":false,"showSkybox":false,"showFlares":true,"showImageEffects":true,"showParticleSystems":true},"in2DMode":false,"pivot":{"x":-0.37182921171188357,"y":0.24442368745803834,"z":-242.95223999023438},"rotation":{"x":0.13321004807949067,"y":-0.6822048425674439,"z":0.12247656285762787,"w":0.7092271447181702},"size":19.46472930908203,"orthographic":false}