{"cameraMode":{"drawMode":0,"name":"Shaded","section":"Shading Mode"},"sceneLighting":false,"audioPlay":false,"sceneViewState":{"showFog":true,"showMaterialUpdate":false,"showSkybox":false,"showFlares":true,"showImageEffects":true,"showParticleSystems":true},"in2DMode":false,"pivot":{"x":0.004470109939575195,"y":0.0013568401336669922,"z":2.1742501258850099},"rotation":{"x":-0.1280611902475357,"y":0.832611620426178,"z":-0.21598270535469056,"w":-0.4936734437942505},"size":2.502861261367798,"orthographic":false}